diff_agent/__init__.py
diff_agent/diff_agent.py
diff_agent-0.1.3.dist-info/LICENSE
diff_agent-0.1.3.dist-info/METADATA
diff_agent-0.1.3.dist-info/WHEEL
diff_agent-0.1.3.dist-info/top_level.txt
diff_agent-0.1.3.dist-info/RECORD
