Metadata-Version: 2.2
Name: diff_agent
Version: 0.1.3
Summary: A tool for automatically committing and summarizing git changes
Home-page: https://github.com/yourusername/diff_agent
Author: Your Name
Author-email: your.email@example.com
License: MIT
Classifier: Programming Language :: Python :: 3
Classifier: License :: OSI Approved :: MIT License
Classifier: Operating System :: OS Independent
Requires-Python: >=3.7
License-File: LICENSE
Requires-Dist: litellm>=0.1.0
Requires-Dist: weave>=0.1.0
Dynamic: author
Dynamic: author-email
Dynamic: classifier
Dynamic: description
Dynamic: description-content-type
Dynamic: home-page
Dynamic: license
Dynamic: requires-dist
Dynamic: requires-python
Dynamic: summary
